ameritrade/__init__.py
ameritrade/auth.py
ameritrade/history.py
ameritrade/quotes.py
ameritrade/settings.py
ameritrade/stock.py
ameritrade/utils.py
ameritrade_python-0.1.2.dist-info/LICENSE
ameritrade_python-0.1.2.dist-info/WHEEL
ameritrade_python-0.1.2.dist-info/METADATA
ameritrade_python-0.1.2.dist-info/RECORD
